<?xml version="1.0" encoding="UTF-8"?>
<record_update table="sp_page">
    <sp_page action="INSERT_OR_UPDATE">
        <category>other</category>
        <css>section.page {&#13;
	background-color: $sp-homepage-bg;&#13;
}&#13;
section.page, main.body {&#13;
    padding-top: 0px !important;&#13;
}&#13;
</css>
        <draft>false</draft>
        <dynamic_title_structure/>
        <id>index3</id>
        <internal>false</internal>
        <public>false</public>
        <roles/>
        <short_description/>
        <sys_class_name>sp_page</sys_class_name>
        <sys_created_by>hartmap</sys_created_by>
        <sys_created_on>2018-04-11 11:38:05</sys_created_on>
        <sys_customer_update>false</sys_customer_update>
        <sys_id>a3f72d5f4f1553008f458a4e0210c723</sys_id>
        <sys_mod_count>2</sys_mod_count>
        <sys_name>index3</sys_name>
        <sys_package display_value="Service Portal ver3" source="x_aegi2_service_po">9907f1c34f5d1300f2a00195f110c7bb</sys_package>
        <sys_policy/>
        <sys_replace_on_upgrade>false</sys_replace_on_upgrade>
        <sys_scope display_value="Service Portal ver3">9907f1c34f5d1300f2a00195f110c7bb</sys_scope>
        <sys_update_name>sp_page_a3f72d5f4f1553008f458a4e0210c723</sys_update_name>
        <sys_updated_by>hartmap</sys_updated_by>
        <sys_updated_on>2018-04-11 11:41:02</sys_updated_on>
        <title>Service Portal</title>
    </sp_page>
    <sys_translated_text action="delete_multiple" query="documentkey=a3f72d5f4f1553008f458a4e0210c723"/>
</record_update>
